blazing_astro/__init__.py
blazing_astro/server.py
blazing_astro/storage.py
blazing_astro/subjects.json
blazing_astro-0.1.0.dist-info/METADATA
blazing_astro-0.1.0.dist-info/WHEEL
blazing_astro-0.1.0.dist-info/entry_points.txt
blazing_astro-0.1.0.dist-info/RECORD
