Metadata-Version: 2.4
Name: blazing-astro
Version: 0.1.0
Summary: An astrological MCP server using Kerykeion
Author-email: Blazing Astro User <user@example.com>
Requires-Python: >=3.10
Requires-Dist: kerykeion
Requires-Dist: mcp[cli]
Requires-Dist: pydantic
